otsclient/__init__.py
otsclient/args.py
otsclient/cache.py
otsclient/cmds.py
otsclient/git.py
otsclient/git_gpg_wrapper.py
otsclient/ots.py
otsclient/tests/__init__.py
otsclient/tests/test_git.py
otsclient/tests/test_prune.py
opentimestamps_client-0.7.1.dist-info/LICENSE
opentimestamps_client-0.7.1.dist-info/METADATA
opentimestamps_client-0.7.1.dist-info/WHEEL
opentimestamps_client-0.7.1.dist-info/entry_points.txt
opentimestamps_client-0.7.1.dist-info/top_level.txt
opentimestamps_client-0.7.1.dist-info/RECORD
