Metadata-Version: 2.1
Name: opentimestamps-client
Version: 0.7.1
Summary: Command-line tool to create and verify OpenTimestamps proofs
Home-page: https://github.com/opentimestamps/opentimestamps-client
Author: Peter Todd
Author-email: pete@petertodd.org
License: LGPL3
Keywords: cryptography timestamping bitcoin
Platform: UNKNOWN
Classifier: Development Status :: 4 - Beta
Classifier: Intended Audience :: Developers
Classifier: Intended Audience :: End Users/Desktop
Classifier: Topic :: Security :: Cryptography
Classifier: License :: OSI Approved :: GNU Lesser General Public License v3 or later (LGPLv3+)
Classifier: Programming Language :: Python :: 3 :: Only
